HERON/__init__.py
HERON/src/ArmaBypass.py
HERON/src/Cases.py
HERON/src/CashFlowUser.py
HERON/src/Components.py
HERON/src/DispatchBypass.py
HERON/src/DispatchManager.py
HERON/src/DispatchPlot.py
HERON/src/Economics.py
HERON/src/Herd.py
HERON/src/Moped.py
HERON/src/NetworkPlot.py
HERON/src/Placeholders.py
HERON/src/SerializationManager.py
HERON/src/ValuedParamHandler.py
HERON/src/__init__.py
HERON/src/_utils.py
HERON/src/base.py
HERON/src/input_definition.py
HERON/src/input_loader.py
HERON/src/main.py
HERON/src/Hybrid2Heron/HYBRID_HERON_keywords.csv
HERON/src/Hybrid2Heron/hybrid2heron_economic.py
HERON/src/TransferFuncs/Factory.py
HERON/src/TransferFuncs/Polynomial.py
HERON/src/TransferFuncs/Ratio.py
HERON/src/TransferFuncs/TransferFunc.py
HERON/src/TransferFuncs/__init__.py
HERON/src/ValuedParams/Activity.py
HERON/src/ValuedParams/Factory.py
HERON/src/ValuedParams/Function.py
HERON/src/ValuedParams/Parametric.py
HERON/src/ValuedParams/ROM.py
HERON/src/ValuedParams/RandomVariable.py
HERON/src/ValuedParams/StaticHistory.py
HERON/src/ValuedParams/SyntheticHistory.py
HERON/src/ValuedParams/ValuedParam.py
HERON/src/ValuedParams/Variable.py
HERON/src/ValuedParams/__init__.py
HERON/src/dispatch/CustomDispatcher.py
HERON/src/dispatch/DispatchState.py
HERON/src/dispatch/Dispatcher.py
HERON/src/dispatch/Factory.py
HERON/src/dispatch/PyomoModelHandler.py
HERON/src/dispatch/PyomoRuleLibrary.py
HERON/src/dispatch/__init__.py
HERON/src/dispatch/putils.py
HERON/src/dispatch/pyomo_dispatch.py
HERON/src/dispatch/twin_pyomo_limited_ramp.py
HERON/src/dispatch/twin_pyomo_test.py
HERON/src/dispatch/twin_pyomo_test_rte.py
HERON/src/validators/ExampleValidator.py
HERON/src/validators/Factory.py
HERON/src/validators/Validator.py
HERON/src/validators/__init__.py
HERON/templates/__init__.py
HERON/templates/cash.xml
HERON/templates/inner.xml
HERON/templates/outer.xml
HERON/templates/template_driver.py
HERON/templates/write_inner.py
heron_ravenframework-0.5.dist-info/METADATA
heron_ravenframework-0.5.dist-info/WHEEL
heron_ravenframework-0.5.dist-info/entry_points.txt
heron_ravenframework-0.5.dist-info/top_level.txt
heron_ravenframework-0.5.dist-info/RECORD
