Metadata-Version: 2.1
Name: heron-ravenframework
Version: 0.5
Summary: HERON plugin for RAVEN framework
Home-page: https://github.com/idaholab/HERON
Requires-Python: >=3.9
Requires-Dist: raven-framework >=3.1
Requires-Dist: teal-ravenframework
Requires-Dist: dill ==0.3.5
Requires-Dist: pyomo ==6.4
Requires-Dist: networkx
Requires-Dist: pyutilib
